melime/__init__.py
melime/explainers/__init__.py
melime/explainers/explainer.py
melime/explainers/local_models/__init__.py
melime/explainers/local_models/local_model_base.py
melime/explainers/local_models/local_model_linear.py
melime/explainers/local_models/local_model_statistics.py
melime/explainers/local_models/local_model_tree.py
melime/explainers/visualizations/__init__.py
melime/explainers/visualizations/plot_importance.py
melime/explainers/visualizations/visualization.py
melime/generators/__init__.py
melime/generators/cnnvae_gen.py
melime/generators/gen_base.py
melime/generators/kde_gen.py
melime/generators/kdepca_gen.py
melime/generators/vae_gen.py
melime/generators/word2vec_gen.py
melime/generators/models/__init__.py
melime/generators/models/gensim_cbow.py
melime/generators/models/torch_word2vec.py
melime-0.3.dist-info/LICENSE.md
melime-0.3.dist-info/METADATA
melime-0.3.dist-info/WHEEL
melime-0.3.dist-info/top_level.txt
melime-0.3.dist-info/RECORD
