Metadata-Version: 2.1
Name: melime
Version: 0.3
Summary: UNKNOWN
Home-page: https://github.com/tiagobotari/melime/
Author: Tiago Botari, Frederik Hvilshøj
Author-email: 
License: MIT License
Platform: UNKNOWN
Requires-Python: >=3.6
Requires-Dist: scikit-learn (>=0.21)
Requires-Dist: torch (>=1.3)
Requires-Dist: torchvision (>=0.4)
Requires-Dist: numpy (>=1.17)
Requires-Dist: matplotlib
Requires-Dist: scikit-image (>=0.17.2)
Requires-Dist: gensim
